setup.py
constantBase.egg-info/PKG-INFO
constantBase.egg-info/SOURCES.txt
constantBase.egg-info/dependency_links.txt
constantBase.egg-info/top_level.txt
pyConstants/__init__.py
pyConstants/constantBase.py
pyConstants/constantWrappers.py