Metadata-Version: 2.1
Name: constantBase
Version: 1.0.0
Summary: Allows for the creation of constants in Python
Home-page: UNKNOWN
Author: LCreations
License: UNKNOWN
Platform: UNKNOWN
Classifier: Programming Language :: Python :: 3
Classifier: License :: OSI Approved :: MIT License
Classifier: Operating System :: OS Independent
Requires-Python: >=3.6
